<?xml version="1.0" encoding="UTF-8"?>
<!--
  Task: Reconcile Oracle LAMB Egresados
  Resource: Oracle LAMB Egresados v2 (OID 6a91f7e1-1b50-4dcf-9c4b-7c0c0e0e0e23)
  Estado: suspended — NO ejecutar automáticamente.
  Activar manualmente desde la UI cuando el piloto de import esté aprobado.
  Horario configurado: 02:00 UTC nightly (cronLikePattern) — inactivo mientras suspended.
  Fase: I6 — IGA UPeU canónico 2026-05-17
-->
<task xmlns="http://midpoint.evolveum.com/xml/ns/public/common/common-3"
      oid="f1a00002-lamb-rec0-0000-000000000002">
    <name>Reconcile Oracle LAMB Egresados</name>
    <ownerRef oid="00000000-0000-0000-0000-000000000002" type="UserType"/>
    <executionStatus>suspended</executionStatus>
    <schedule>
        <recurrence>recurring</recurrence>
        <cronLikePattern>0 0 2 * * ?</cronLikePattern>
    </schedule>
    <activity>
        <work>
            <reconciliation>
                <resourceRef oid="6a91f7e1-1b50-4dcf-9c4b-7c0c0e0e0e23" type="ResourceType"/>
            </reconciliation>
        </work>
    </activity>
</task>
